pomop_queue/__init__.py
pomop_queue/cli_parser.py
pomop_queue/task_queue.py
pomop_queue-0.1.0.dist-info/LICENSE
pomop_queue-0.1.0.dist-info/METADATA
pomop_queue-0.1.0.dist-info/WHEEL
pomop_queue-0.1.0.dist-info/entry_points.txt
pomop_queue-0.1.0.dist-info/top_level.txt
pomop_queue-0.1.0.dist-info/RECORD
