Metadata-Version: 2.1
Name: pomop-queue
Version: 0.1.0
Summary: Using Pomodoro and Task Queue to handle tasks productively
Home-page: UNKNOWN
Author: Tung Son Do
Author-email: dosontung007@gmail.com
License: MIT
Platform: UNKNOWN
Requires-Dist: pomop
